kagu/__init__.py
kagu/arguments/__init__.py
kagu/arguments/base_arguments.py
kagu/core/__init__.py
kagu/core/loss.py
kagu/datasets/__init__.py
kagu/datasets/kagu_dataset.py
kagu/models/__init__.py
kagu/models/model.py
kagu/trainers/__init__.py
kagu/trainers/trainer.py
kagu_torch-0.0.1.dist-info/LICENSE
kagu_torch-0.0.1.dist-info/METADATA
kagu_torch-0.0.1.dist-info/WHEEL
kagu_torch-0.0.1.dist-info/top_level.txt
kagu_torch-0.0.1.dist-info/RECORD
