Metadata-Version: 2.1
Name: kagu-torch
Version: 0.0.1
Summary: Official implementation of Towards Automated Ethogramming: Cognitively-Inspired Event Segmentation for Streaming Wildlife Video Monitoring
Home-page: https://ramymounir.com/docs/AutomatedEthogramming/
Author: Ramy Mounir
Classifier: Programming Language :: Python :: 3
Classifier: License :: Free for non-commercial use
Requires-Python: >=3.10
License-File: LICENSE
Requires-Dist: torch >=2.0.0
Requires-Dist: ddpw >=5.1.1
Requires-Dist: opencv-python-headless
Requires-Dist: tqdm
Requires-Dist: torchvision
Requires-Dist: tensorboard
